miblepy-0.4.6.dist-info/dependency_links.txt
miblepy-0.4.6.dist-info/entry_points.txt
miblepy-0.4.6.dist-info/METADATA
miblepy-0.4.6.dist-info/top_level.txt
miblepy-0.4.6.dist-info/WHEEL
miblepy/__init__.py
miblepy/deviceplugin.py
miblepy/mible/__init__.py
miblepy/mible/cli.py
miblepy/devices/flowercare.py
miblepy/devices/__init__.py
miblepy/devices/bodycompscale.py
miblepy/devices/lywsd03mmc.py
miblepy/devices/xbm/__init__.py
miblepy-0.4.6.dist-info/LICENSE
miblepy-0.4.6.dist-info/RECORD