Metadata-Version: 2.1
Name: miblepy
Version: 0.4.6
Summary: miblepy fetches data from various (Xiaomi/Mijia/Mi) Bluetooth LE devices and push it to a MQTT broker in a coordinated, sequential manner.
Project-URL: Homepage, https://github.com/benleb/miblepy
Project-URL: Repository, https://github.com/benleb/miblepy
Author: Ben Lebherz
Author-email: git@benleb.de
License: MIT
Requires-Python: ==3.*,>=3.8.0
Keywords: bluetooth,smart-home,sensor,xiaomi,home-assistant
Classifier: Development Status :: 4 - Beta
Classifier: Environment :: Console
Classifier: Intended Audience :: Developers
Classifier: Intended Audience :: Education
Classifier: License :: OSI Approved :: MIT License
Classifier: Operating System :: POSIX :: Linux
Classifier: Programming Language :: Python :: 3
Classifier: Programming Language :: Python :: 3.8
Classifier: Topic :: Home Automation
Requires-Dist: bandit==1.*,>=1.6.2; extra == "dev"
Requires-Dist: black==19.*,>=19.10.0.b0; extra == "dev"
Requires-Dist: bluepy==1.*,>=1.3.0
Requires-Dist: click==7.*,>=7.1.2
Requires-Dist: flake8==3.*,>=3.8.1; extra == "dev"
Requires-Dist: isort==4.*,>=4.3.21; extra == "dev"
Requires-Dist: mypy==0.*,>=0.770.0; extra == "dev"
Requires-Dist: paho-mqtt==1.*,>=1.5.0
Requires-Dist: pycodestyle==2.*,>=2.6.0; extra == "dev"
Requires-Dist: pytest==5.*,>=5.2.0; extra == "dev"
Requires-Dist: tomlkit==0.*,>=0.6.0
Provides-Extra: dev
